{
  "id": "animal-crossing/diy-bug-islands",
  "title": "DIY Bug Islands",
  "description": "Got an excess of Nook Miles? Turn those Nook Miles into bells with some DIY bug islands. Strap in, this is a long one!!",
  "source": "@site/docs\\animal-crossing\\diy-bug-islands.md",
  "permalink": "/docs/animal-crossing/diy-bug-islands",
  "editUrl": "https://github.com/facebook/docusaurus/edit/master/website/docs/animal-crossing/diy-bug-islands.md",
  "sidebar": "someSidebar",
  "previous": {
    "title": "Tool Durability",
    "permalink": "/docs/animal-crossing/tool-durability"
  },
  "next": {
    "title": "Fake Art Checker",
    "permalink": "/docs/animal-crossing/fake-art-checker"
  }
}